setup.py
multiqueue/__init__.py
multiqueue.egg-info/PKG-INFO
multiqueue.egg-info/SOURCES.txt
multiqueue.egg-info/dependency_links.txt
multiqueue.egg-info/top_level.txt