Metadata-Version: 1.1
Name: multiqueue
Version: 0.1.6
Summary: Sometimes when you use the Queue class in Python, you need to get an item from any of several queues. This small module implements an easy solution for this problem.
Home-page: https://github.com/leio10/python-multiqueue
Author: leio10
Author-email: leiodd@gmail.com
License: BSD
Platform: UNKNOWN
Classifier: Development Status :: 4 - Beta
Classifier: License :: OSI Approved :: BSD License
Classifier: Operating System :: OS Independent
Classifier: Topic :: Software Development :: Libraries :: Python Modules
